<?xml version="1.0" encoding="UTF-8"?>
<objects serializationModel="Studio.02.00.00">
	<object class="AudioFile" id="{24e12cfd-9a1f-41b8-bb9e-3c3bbd21c6ee}">
		<property name="assetPath">
			<value>Jump/JumpLandingDirt02.wav</value>
		</property>
		<property name="frequencyInKHz">
			<value>44.0999985</value>
		</property>
		<property name="channelCount">
			<value>2</value>
		</property>
		<property name="length">
			<value>1.0612244897959184</value>
		</property>
		<relationship name="masterAssetFolder">
			<destination>{26d32b25-4e24-45c7-96d4-8dede004b67c}</destination>
		</relationship>
	</object>
</objects>
