<?xml version="1.0" encoding="UTF-8"?>
<objects serializationModel="Studio.02.00.00">
	<object class="AudioFile" id="{63eee276-9ba6-4468-b9c3-e08d9bbc66d8}">
		<property name="assetPath">
			<value>MusicErick/enemyB_outro.wav</value>
		</property>
		<property name="frequencyInKHz">
			<value>48</value>
		</property>
		<property name="channelCount">
			<value>2</value>
		</property>
		<property name="length">
			<value>7.5590624999999996</value>
		</property>
		<relationship name="masterAssetFolder">
			<destination>{26d32b25-4e24-45c7-96d4-8dede004b67c}</destination>
		</relationship>
	</object>
</objects>
